asf_cherry_pick/__init__.py
asf_cherry_pick/asf_cherry_pick.py
asf_cherry_pick/get_missings.py
asf_cherry_pick-2.0.3.dist-info/licenses/LICENSE
testing/test_asf_cherry_pick.py
asf_cherry_pick-2.0.3.dist-info/METADATA
asf_cherry_pick-2.0.3.dist-info/WHEEL
asf_cherry_pick-2.0.3.dist-info/entry_points.txt
asf_cherry_pick-2.0.3.dist-info/top_level.txt
asf_cherry_pick-2.0.3.dist-info/RECORD
