Metadata-Version: 2.4
Name: asf_cherry_pick
Version: 2.0.3
Summary: Python package for cherry picking Data into asf
Author-email: Franck Thollard <franck.thollard@univ-grenoble-alpes.fr>
License: BSD 3-Clause License
Project-URL: Homepage, https://gricad-gitlab.univ-grenoble-alpes.fr/NSBAS/asf_cherry_pick
Classifier: Programming Language :: Python :: 3 :: Only
Classifier: License :: OSI Approved :: GNU General Public License v3 (GPLv3)
Classifier: Intended Audience :: Science/Research
Requires-Python: >=3.10
License-File: LICENSE
Requires-Dist: asf_search==11.0.0
Requires-Dist: fastkml
Requires-Dist: lxml
Requires-Dist: pytest>=9.0.2
Requires-Dist: remotezip>=0.10.0
Dynamic: license-file
